xyapi/__init__.py
xyapi/exception.py
xyapi/response.py
xyapi-0.0.2.dist-info/LICENSE
xyapi-0.0.2.dist-info/METADATA
xyapi-0.0.2.dist-info/WHEEL
xyapi-0.0.2.dist-info/top_level.txt
xyapi-0.0.2.dist-info/RECORD
